{"cameraMode":{"drawMode":0,"name":"Shaded","section":"Shading Mode"},"sceneLighting":false,"audioPlay":false,"sceneViewState":{"showFog":true,"showMaterialUpdate":false,"showSkybox":false,"showFlares":true,"showImageEffects":true,"showParticleSystems":true},"in2DMode":false,"pivot":{"x":0.13989567756652833,"y":-1.9515471458435059,"z":0.30366086959838869},"rotation":{"x":0.5538313984870911,"y":-0.1419670730829239,"z":0.09648428857326508,"w":0.814763605594635},"size":3.8786394596099855,"orthographic":false}